deepdrr/__init__.py
deepdrr/common.py
deepdrr/downsample_tool.py
deepdrr/load_dicom.py
deepdrr/load_dicom_tool.py
deepdrr/logging.py
deepdrr/network_segmentation.py
deepdrr/segmentation.py
deepdrr/vis.py
deepdrr/annotations/__init__.py
deepdrr/annotations/fiducials.py
deepdrr/annotations/line_annotation.py
deepdrr/device/__init__.py
deepdrr/device/camera_projection_device.py
deepdrr/device/carm.py
deepdrr/device/device.py
deepdrr/device/mobile_carm.py
deepdrr/device/simple_device.py
deepdrr/geo/__init__.py
deepdrr/instruments/__init__.py
deepdrr/instruments/base.py
deepdrr/material/__init__.py
deepdrr/material/coefficient.py
deepdrr/material/log_interp.py
deepdrr/material/mappings.py
deepdrr/material/material.py
deepdrr/material/material_decompositions/10_Ne_Neon
deepdrr/material/material_decompositions/11_Na_Sodium
deepdrr/material/material_decompositions/12_Mg_Magnesium
deepdrr/material/material_decompositions/13_Al_Aluminum
deepdrr/material/material_decompositions/14_Si_Silicon
deepdrr/material/material_decompositions/15_P_Phosphorus
deepdrr/material/material_decompositions/16_S_Sulfur
deepdrr/material/material_decompositions/17_Cl_Chlorine
deepdrr/material/material_decompositions/18_Ar_Argon
deepdrr/material/material_decompositions/19_K_Potassium
deepdrr/material/material_decompositions/1_H_Hydrogen
deepdrr/material/material_decompositions/20_Ca_Calcium
deepdrr/material/material_decompositions/21_Sc_Scandium
deepdrr/material/material_decompositions/22_Ti_Titanium
deepdrr/material/material_decompositions/23_V_Vanadium
deepdrr/material/material_decompositions/24_Cr_Chromium
deepdrr/material/material_decompositions/25_Mn_Manganese
deepdrr/material/material_decompositions/26_Fe_Iron
deepdrr/material/material_decompositions/27_Co_Cobalt
deepdrr/material/material_decompositions/28_Ni_Nickel
deepdrr/material/material_decompositions/29_Cu_Copper
deepdrr/material/material_decompositions/2_He_Helium
deepdrr/material/material_decompositions/30_Zn_Zinc
deepdrr-1.2.2.dist-info/licenses/LICENSE
deepdrr-1.2.2.dist-info/METADATA
deepdrr-1.2.2.dist-info/WHEEL
deepdrr-1.2.2.dist-info/top_level.txt
deepdrr-1.2.2.dist-info/RECORD
