Metadata-Version: 2.4
Name: deepdrr
Version: 1.2.2
Summary: A Catalyst for Machine Learning in Fluoroscopy-guided Procedures.
Author: Cong Gao, Liam J. Wang, Max Judish
Author-email: "Benjamin D. Killeen" <killeen@jhu.edu>, Mathias Unberath <unberath@jhu.edu>
License:                     GNU GENERAL PUBLIC LICENSE
Requires-Python: >=3.7
License-File: LICENSE
Requires-Dist: numpy<2.0.0
Requires-Dist: torch
Requires-Dist: torchvision
Requires-Dist: nibabel
Requires-Dist: scikit-image
Requires-Dist: pydicom
Requires-Dist: scipy
Requires-Dist: pyvista
Requires-Dist: pynrrd
Requires-Dist: rich
Requires-Dist: tqdm
Requires-Dist: opencv-python
Requires-Dist: seaborn
Requires-Dist: graphviz
Requires-Dist: pyglet>=1.4.11
Requires-Dist: PyOpenGL==3.1.6
Requires-Dist: PyOpenGL_accelerate>=3.1.7
Requires-Dist: arcade-pyrender
Requires-Dist: trimesh
Requires-Dist: cuda-python
Requires-Dist: killeengeo
Requires-Dist: strenum
Requires-Dist: open3d
Provides-Extra: dev
Requires-Dist: black; extra == "dev"
Requires-Dist: pytest; extra == "dev"
Requires-Dist: trame; extra == "dev"
Requires-Dist: ipykernel; extra == "dev"
Requires-Dist: ipywidgets; extra == "dev"
Provides-Extra: cuda102
Requires-Dist: cupy-cuda102; extra == "cuda102"
Provides-Extra: cuda110
Requires-Dist: cupy-cuda110; extra == "cuda110"
Provides-Extra: cuda111
Requires-Dist: cupy-cuda111; extra == "cuda111"
Provides-Extra: cuda11x
Requires-Dist: cupy-cuda11x; extra == "cuda11x"
Provides-Extra: cuda12x
Requires-Dist: cupy-cuda12x; extra == "cuda12x"
Dynamic: license-file
